pm_slack/__init__.py
pm_slack/constants.py
pm_slack/köfte.jpg
pm_slack/main.py
pm_slack/py.typed
pm_slack/templates/__init__.py
pm_slack/templates/_templates.py
pm_slack-0.4.6.dist-info/LICENSE
pm_slack-0.4.6.dist-info/METADATA
pm_slack-0.4.6.dist-info/WHEEL
pm_slack-0.4.6.dist-info/RECORD
