Metadata-Version: 2.1
Name: pm_slack
Version: 0.4.6
Summary: A Slack Library for Paket Mutfak
License: MIT
Author: Paket Mutfak Dev Team
Author-email: dev@paketmutfak.com.tr
Requires-Python: >=3.8,<4.0
Classifier: License :: OSI Approved :: MIT License
Classifier: Programming Language :: Python :: 3
Classifier: Programming Language :: Python :: 3.8
Classifier: Programming Language :: Python :: 3.9
Classifier: Programming Language :: Python :: 3.10
Classifier: Programming Language :: Python :: 3.11
Classifier: Programming Language :: Python :: 3.12
Requires-Dist: slack-sdk (>=3.21.3,<4.0.0)
